dorplan/__init__.py
dorplan/app.py
dorplan/cli.py
dorplan/example/example.py
dorplan/example/example_cli.py
dorplan/shared/tools.py
dorplan/tests/__init__.py
dorplan/tests/dummy_ui.py
dorplan/tests/test_app.py
dorplan/tests/test_cli.py
dorplan/tests/test_solvers.py
dorplan/tests/data/graph_coloring/__init__.py
dorplan/tests/data/graph_coloring/core/__init__.py
dorplan/tests/data/graph_coloring/core/experiment.py
dorplan/tests/data/graph_coloring/core/instance.py
dorplan/tests/data/graph_coloring/core/solution.py
dorplan/tests/data/graph_coloring/data/gc_4_1
dorplan/tests/data/graph_coloring/data/gc_50_1
dorplan/tests/data/graph_coloring/report/report.qmd
dorplan/tests/data/graph_coloring/schemas/config.json
dorplan/tests/data/graph_coloring/schemas/input.json
dorplan/tests/data/graph_coloring/schemas/output.json
dorplan/tests/data/graph_coloring/schemas/solution_checks.json
dorplan/tests/data/graph_coloring/solvers/__init__.py
dorplan/tests/data/graph_coloring/solvers/cp_model.py
dorplan/tests/data/graph_coloring/solvers/mip_model.py
dorplan/tests/data/graph_coloring/solvers/networkx.py
dorplan/tests/data/graph_coloring/solvers/timefold.py
dorplan/ui/gui.py
dorplan/workers/__init__.py
dorplan/workers/base_worker.py
dorplan/workers/log_tailer.py
dorplan/workers/optimworker.py
dorplan/workers/optimworker_multi.py
dorplan/workers/repWorker.py
dorplan-0.11.2.dist-info/licenses/AUTHORS.md
dorplan-0.11.2.dist-info/licenses/LICENSE
dorplan-0.11.2.dist-info/METADATA
dorplan-0.11.2.dist-info/WHEEL
dorplan-0.11.2.dist-info/top_level.txt
dorplan-0.11.2.dist-info/RECORD
