Metadata-Version: 2.4
Name: dorplan
Version: 0.11.2
Summary: Desktop OR planner
Author-email: Franco Peschiera <pchtsp@gmail.com>
Maintainer-email: Franco Peschiera <pchtsp@gmail.com>
Keywords: Mathematical,Optimization,solver,GUI,desktop,cross-platform
Classifier: Programming Language :: Python
Classifier: Topic :: Software Development
Classifier: Topic :: Software Development :: Libraries
Classifier: Topic :: Software Development :: Libraries :: Python Modules
Requires-Python: >=3.10
License-File: LICENSE
License-File: AUTHORS.md
Requires-Dist: cornflow-client-pchtsp
Requires-Dist: PySide6
Requires-Dist: click
Provides-Extra: reports
Requires-Dist: quarto; extra == "reports"
Requires-Dist: quarto-cli; sys_platform == "linux" and extra == "reports"
Requires-Dist: papermill; extra == "reports"
Requires-Dist: matplotlib; extra == "reports"
Provides-Extra: example
Requires-Dist: orloge; extra == "example"
Requires-Dist: pulp; extra == "example"
Requires-Dist: highspy; extra == "example"
Requires-Dist: ortools; extra == "example"
Requires-Dist: networkx; extra == "example"
Requires-Dist: timefold; extra == "example"
Requires-Dist: pydantic; extra == "example"
Dynamic: license-file
